tatau/__init__.py
tatau/_version.py
tatau/dataset/__init__.py
tatau/dataset/remap.py
tatau/dataset/keras/__init__.py
tatau/dataset/keras/image.py
tatau/fs/__init__.py
tatau/fs/dirs.py
tatau/nn/__init__.py
tatau/nn/class_loader.py
tatau/nn/keras/__init__.py
tatau/nn/keras/model.py
tatau/nn/keras/progress.py
tatau/nn/keras/serializer.py
tatau/nn/keras/summarizer/__init__.py
tatau/nn/keras/summarizer/mean.py
tatau/nn/keras/summarizer/median.py
tatau/nn/keras/utils/__init__.py
tatau/nn/keras/utils/dataset.py
tatau/nn/tatau/__init__.py
tatau/nn/tatau/model.py
tatau/nn/tatau/progress.py
tatau/nn/tatau/serializer.py
tatau/nn/tatau/callbacks/__init__.py
tatau/nn/tatau/callbacks/callback.py
tatau/nn/tatau/callbacks/progress.py
tatau/nn/tatau/summarizer/__init__.py
tatau/nn/tatau/summarizer/summarizer.py
tatau/nn/torch/__init__.py
tatau/nn/torch/dataset.py
tatau/nn/torch/model.py
tatau/nn/torch/serializer.py
tatau/nn/torch/models/__init__.py
tatau/nn/torch/models/resnet.py
tatau/nn/torch/summarizer/__init__.py
tatau/nn/torch/summarizer/mean.py
tatau/nn/torch/summarizer/median.py
tatau/nn/torch/summarizer/model.py
tatau/nn/torch/summarizer/opt.py
tatau/nn/torch/summarizer/weights.py
tatau/nn/torch/utils/__init__.py
tatau/nn/torch/utils/dataset.py
tatau/nn/torch/utils/fast_preprocessing.py
tests/__init__.py
tests/test_keras.py
tests/test_torch.py
tatau-0.0.11.dev0.dist-info/LICENSE
tatau-0.0.11.dev0.dist-info/METADATA
tatau-0.0.11.dev0.dist-info/WHEEL
tatau-0.0.11.dev0.dist-info/top_level.txt
tatau-0.0.11.dev0.dist-info/RECORD
